sarlib/__init__.py
sarlib/sarlib.py
sarlib-0.0.5.dist-info/licenses/LICENSE.md
sarlib-0.0.5.dist-info/METADATA
sarlib-0.0.5.dist-info/WHEEL
sarlib-0.0.5.dist-info/top_level.txt
sarlib-0.0.5.dist-info/RECORD
