Metadata-Version: 2.4
Name: sarlib
Version: 0.0.5
Summary: Statistical Agnostic Regression Library
Author: SiPBA Group
License-Expression: GPL-3.0-or-later
Project-URL: Homepage, https://github.com/SiPBA/sar/
Project-URL: Issues, https://github.com/SiPBA/sar/issues
Classifier: Programming Language :: Python :: 3
Classifier: Operating System :: OS Independent
Requires-Python: >=3.8
License-File: LICENSE.md
Requires-Dist: numpy
Requires-Dist: matplotlib
Requires-Dist: scipy
Requires-Dist: scikit-learn
Requires-Dist: statsmodels
Dynamic: license-file
